genesis_models/base.py
genesis_models/models.py
genesis_models-0.1.2.dist-info/METADATA
genesis_models-0.1.2.dist-info/WHEEL
genesis_models-0.1.2.dist-info/RECORD
