Metadata-Version: 2.1
Name: genesis-models
Version: 0.1.2
Summary: Shared database models for Genesis services
Author: stevenge
Author-email: stevenge@godscode.com.cn
Requires-Python: >=3.12,<4.0
Classifier: Programming Language :: Python :: 3
Classifier: Programming Language :: Python :: 3.12
Requires-Dist: sqlalchemy (>=1.4.0,<2.0.0)
